resource_ingest_guide_schema/_version.py
resource_ingest_guide_schema/datamodel/__init__.py
resource_ingest_guide_schema/datamodel/resource_ingest_guide_schema.py
resource_ingest_guide_schema/schema/resource_ingest_guide_schema.yaml
resource_ingest_guide_schema-0.1.3.dist-info/METADATA
resource_ingest_guide_schema-0.1.3.dist-info/WHEEL
resource_ingest_guide_schema-0.1.3.dist-info/licenses/LICENSE
resource_ingest_guide_schema-0.1.3.dist-info/RECORD
