Metadata-Version: 2.4
Name: resource_ingest_guide_schema
Version: 0.1.3
Summary: This is the project description.
Author-email: Sierra Moxon <smoxon@lbl.gov>
License: MIT
License-File: LICENSE
Requires-Python: >=3.9
Requires-Dist: click
Requires-Dist: jinja2
Requires-Dist: linkml-runtime>=1.1.24
Requires-Dist: linkml>=1.9.3
Requires-Dist: pyyaml
Provides-Extra: dev
Requires-Dist: jupyter>=1.0.0; extra == 'dev'
Requires-Dist: linkml>=1.3.5; extra == 'dev'
Requires-Dist: mkdocs-material>=8.2.8; extra == 'dev'
Requires-Dist: mkdocs-mermaid2-plugin>=1.1.1; extra == 'dev'
Requires-Dist: mknotebooks>=0.8.0; extra == 'dev'
Requires-Dist: schemasheets>=0.1.14; extra == 'dev'
